enig
