Metadata-Version: 2.1
Name: enig
Version: 0.1.1
Summary: Testing installation of Package
Home-page: https://github.com/Topkinsme/enigma_machine
Author: Topkinsme
License: GNU GPL v3
Download-URL: https://github.com/Topkinsme/enigma_machine/archive/refs/tags/0.1.1.tar.gz
Keywords: enigma,enigma_machine,topkinsme,enig
Platform: UNKNOWN
Classifier: Development Status :: 3 - Alpha
Classifier: Intended Audience :: Developers
Classifier: Topic :: Software Development :: Documentation
Classifier: License :: Other/Proprietary License
Classifier: Programming Language :: Python :: 3
Classifier: Programming Language :: Python :: 3.7
Classifier: Programming Language :: Python :: 3.8
Classifier: Programming Language :: Python :: 3.9
